stofware_client/__init__.py
stofware_client/client.py
stofware_client_sdk-0.1.3.dist-info/LICENSE
stofware_client_sdk-0.1.3.dist-info/METADATA
stofware_client_sdk-0.1.3.dist-info/WHEEL
stofware_client_sdk-0.1.3.dist-info/top_level.txt
stofware_client_sdk-0.1.3.dist-info/RECORD
