Metadata-Version: 2.1
Name: stofware-client-sdk
Version: 0.1.3
Summary: A client SDK for interacting with the Stofware API
Home-page: https://github.com/stofloos/stofware-python-client-sdk
Author: Stofloos
Author-email: robin@stofloos.nl
License: MIT
Classifier: Programming Language :: Python :: 3
Classifier: License :: OSI Approved :: MIT License
Classifier: Operating System :: OS Independent
Requires-Python: >=3.6
License-File: LICENSE
Requires-Dist: requests >=2.0.0
